gradio_highlightcode/__init__.py
gradio_highlightcode/highlightcode.py
gradio_highlightcode/highlightcode.pyi
gradio_highlightcode/templates/component/Index-L_ZBJKjg.js
gradio_highlightcode/templates/component/clike-DxjBFHnq.js
gradio_highlightcode/templates/component/dockerfile-CEE6bo6a.js
gradio_highlightcode/templates/component/frontmatter-BMbI4hyO.js
gradio_highlightcode/templates/component/index-BPxCOn3e.js
gradio_highlightcode/templates/component/index-BYQMQ1So.js
gradio_highlightcode/templates/component/index-Bi7mHvLU.js
gradio_highlightcode/templates/component/index-CDufdbe3.js
gradio_highlightcode/templates/component/index-DJkqcLh9.js
gradio_highlightcode/templates/component/index-DmEhOoM7.js
gradio_highlightcode/templates/component/index-x22TQt1o.js
gradio_highlightcode/templates/component/index.js
gradio_highlightcode/templates/component/r-Bz1d3XP0.js
gradio_highlightcode/templates/component/shell-C0C2sNA_.js
gradio_highlightcode/templates/component/sql-uoWIYwDX.js
gradio_highlightcode/templates/component/style.css
gradio_highlightcode/templates/component/yaml-Dt6Tp2eU.js
gradio_highlightcode/templates/example/index.js
gradio_highlightcode/templates/example/style.css
gradio_highlightcode-0.0.9.dist-info/METADATA
gradio_highlightcode-0.0.9.dist-info/WHEEL
gradio_highlightcode-0.0.9.dist-info/RECORD
