Metadata-Version: 2.3
Name: gradio_highlightcode
Version: 0.0.9
Summary: Inference from: https://pypi.org/project/gradio-highlightedcode/   Update Custom Package to the Latest Gradio Code (Support for C, C++...) and optimized invocation methods.
Author-email: Nseven <a0939660914@gmail.com>
License-Expression: Apache-2.0
Keywords: gradio-custom-component,gradio-template-Code
Classifier: Development Status :: 3 - Alpha
Classifier: Operating System :: OS Independent
Classifier: Programming Language :: Python :: 3
Classifier: Programming Language :: Python :: 3 :: Only
Classifier: Programming Language :: Python :: 3.8
Classifier: Programming Language :: Python :: 3.9
Classifier: Programming Language :: Python :: 3.10
Classifier: Programming Language :: Python :: 3.11
Classifier: Topic :: Scientific/Engineering
Classifier: Topic :: Scientific/Engineering :: Artificial Intelligence
Classifier: Topic :: Scientific/Engineering :: Visualization
Requires-Python: >=3.8
Requires-Dist: gradio<5.0,>=4.0
Provides-Extra: dev
Requires-Dist: build; extra == 'dev'
Requires-Dist: twine; extra == 'dev'
